Twitter_Frontend_API/__init__.py
Twitter_Frontend_API/main.py
Twitter_Frontend_API-1.1.1.dist-info/METADATA
Twitter_Frontend_API-1.1.1.dist-info/WHEEL
Twitter_Frontend_API-1.1.1.dist-info/top_level.txt
Twitter_Frontend_API-1.1.1.dist-info/RECORD
